{
  "hash": "92e36e35",
  "configHash": "e57697d5",
  "lockfileHash": "aa2293ca",
  "browserHash": "7610e050",
  "optimized": {
    "react/jsx-dev-runtime": {
      "src": "../../node_modules/react/jsx-dev-runtime.js",
      "file": "react_jsx-dev-runtime.js",
      "fileHash": "d2b38b65",
      "needsInterop": true
    },
    "react-dom/client": {
      "src": "../../node_modules/react-dom/client.js",
      "file": "react-dom_client.js",
      "fileHash": "3f37807f",
      "needsInterop": true
    },
    "react-router-dom": {
      "src": "../../node_modules/react-router-dom/dist/index.js",
      "file": "react-router-dom.js",
      "fileHash": "0a570321",
      "needsInterop": false
    },
    "react": {
      "src": "../../node_modules/react/index.js",
      "file": "react.js",
      "fileHash": "e44829d7",
      "needsInterop": true
    },
    "axios": {
      "src": "../../node_modules/axios/index.js",
      "file": "axios.js",
      "fileHash": "5e48d747",
      "needsInterop": false
    },
    "jwt-decode": {
      "src": "../../node_modules/jwt-decode/build/esm/index.js",
      "file": "jwt-decode.js",
      "fileHash": "9c78d132",
      "needsInterop": false
    }
  },
  "chunks": {
    "chunk-PXJLUKTU": {
      "file": "chunk-PXJLUKTU.js"
    },
    "chunk-FQO5W7GE": {
      "file": "chunk-FQO5W7GE.js"
    },
    "chunk-ZS7NZCD4": {
      "file": "chunk-ZS7NZCD4.js"
    }
  }
}